Workbook

Sheet Sheet1
A1: Order number | B1: Lineitem name | C1: Lineitem sku | D1: Lineitem quantity | E1: Shipping Name | F1: Shipping Street | G1: Shipping Address1 | H1: Shipping City | I1: Shipping Zip | J1: Shipping Province | K1: Shipping Country | L1: Shipping Phone
A2: 3826836476-003Ebony | B2: Bamboo fan | C2: 68e09d0ae1ca9 | D2: =Chumdecor!F5 -> 1 | E2: =Chumdecor!E5 -> Christine Banihashemi | F2: 5540 Eden Roc Dr | H2: GRANITE BAY | I2: 95746 | J2: =[1]Chumdecor!W2 -> CA | K2: =Chumdecor!Y5 -> United States
A3: 3830794506-001Ebony | B3: Bamboo fan | C3: 68e09d0ae1ca9 | D3: =Chumdecor!F6 -> 1 | E3: =Chumdecor!E6 -> Jordyn Navarro | F3: 603 Wright Valley Rd | H3: SMITHVILLE | I3: 64089 | J3: =[1]Chumdecor!W3 -> MO | K3: =Chumdecor!Y6 -> United States
A4: 3831344546-002Red | B4: Bamboo fan | C4: 68e09d0ae1ca9 | D4: =Chumdecor!F7 -> 1 | E4: =Chumdecor!E7 -> Miosoti Jerez Lara | F4: 26 Jennifer Dr | H4: CONCORD | I4: 3301 | J4: =[1]Chumdecor!W4 -> NH | K4: =Chumdecor!Y7 -> United States
A5: 3832024462-003pink | B5: Bamboo fan | C5: 68e09d0ae1ca9 | D5: =Chumdecor!F8 -> 1 | E5: =Chumdecor!E8 -> Aaron Rickards | F5: 1A MILLENNIUM CT | H5: DROUIN | I5: 3818 | J5: =[1]Chumdecor!W5 -> VIC | K5: =Chumdecor!Y8 -> Australia
A6: 3831823324-000terracotta | B6: Bamboo fan | C6: 68e09d0ae1ca9 | D6: =Chumdecor!F9 -> 1 | E6: =Chumdecor!E9 -> India Krug | F6: 201 Osage Ln | H6: Pittsburgh | I6: 15208-2755 | J6: =[1]Chumdecor!W6 -> PA | K6: =Chumdecor!Y9 -> United States
A7: 3830256876-001terracotta | B7: Bamboo fan | C7: 68e09d0ae1ca9 | D7: =Chumdecor!F10 -> 1 | E7: =Chumdecor!E10 -> Ruby Victoria Rose Edwards | F7: 9/188 The Parade | H7: Ascot Vale | I7: 3032 | J7: =[1]Chumdecor!W7 -> VIC | K7: =Chumdecor!Y10 -> Australia
A8: 3832337461-000terracotta | B8: Bamboo fan | C8: 68e09d0ae1ca9 | D8: =Chumdecor!F11 -> 1 | E8: =Chumdecor!E11 -> Mervette Rosewell | F8: 171 Bateau Bay Rd | H8: Bateau Bay | I8: 2261 | J8: =[1]Chumdecor!W8 -> NSW | K8: =Chumdecor!Y11 -> Australia
A9: 3832306093-000terracotta | B9: Bamboo fan | C9: 68e09d0ae1ca9 | D9: =Chumdecor!F12 -> 1 | E9: =Chumdecor!E12 -> Stephanie Younes | F9: 1543 Dingens Avenue | H9: Windermere | I9: 34786 | J9: =[1]Chumdecor!W9 -> FL | K9: =Chumdecor!Y12 -> United States

Sheet Chumdecor
A1: NGÀY ĐI ĐƠN | B1: Ngày đơn hàng | C1: Item Name | D1: Buyer | E1: Ship Name | F1: Quantity | G1: Price | H1: Coupon Code | I1: Coupon Details | J1: Discount Amount | K1: Shipping Discount | L1: Order Shipping | M1: Order Sales Tax | N1: Item Total | O1: Currency | P1: Transaction ID | Q1: Listing ID | R1: Date Paid | S1: Date Shipped | T1: Ship Address1 | U1: Ship Address2 | V1: Ship City | W1: Ship State | X1: Ship Zipcode | Y1: Ship Country | Z1: Order ID | AA1: Variations | AB1: Order Type | AC1: Listings Type | AD1: Payment Type | AE1: InPerson Discount | AF1: InPerson Location | AG1: VAT Paid by Buyer | AH1: SKU
A2: 45947 | B2: 45947 | C2: Bamboo Fan Wall Decor, Folding Fan, Boho Wall Decor, Japanese Wall Art, Wall Decor Fan, Vintage fan, Boho Wall Hanging, Fan Headboard | D2: Camille (5n5xvbjvk05s3c7d) | E2: Camille Dumetz | F2: 1 | G2: SALE50 | H2: SALE50 - % off | I2: 55.99 | J2: 0 | K2: 55 | L2: 0 | M2: 111.98 | N2: USD | O2: 4770000000 | P2: 1780000000 | Q2: ######## | S2: Camille Dumetz | T2: 281 Rue Du Faubourg Des Postes | V2: Lille | W2: Nord | X2: 59000 | Y2: France | Z2: 3832157327 | AA2: Width:48 Inches,STYLE:Terracotta,Personalization:+33669158519 | AB2: online | AC2: listing | AD2: online_cc | AG2: 0 | AH2: SKU00010-002Terracotta
A3: 45947 | B3: 45947 | C3: Bamboo Fan Wall Decor, Folding Fan, Boho Wall Decor, Japanese Wall Art, Wall Decor Fan, Vintage fan, Boho Wall Hanging, Fan Headboard | D3: Lyris (l1neekoz) | E3: Lyris Thien Gordon | F3: 1 | G3: SALE50 | H3: SALE50 - % off | I3: 74.99 | J3: 0 | K3: 0 | L3: 0 | M3: 149.98 | N3: USD | O3: 4780000000 | P3: 1880000000 | Q3: ######## | S3: Lyris Thien Gordon | T3: 5625 Republic Of Texas Blvd | V3: Austin | W3: TX | X3: 78735-6514 | Y3: United States | Z3: 3831484853 | AA3: Width:63 Inches,Personalization:5124315390 | AB3: online | AC3: listing | AD3: online_cc | AG3: 0 | AH3: SKU00010-005redpink
A4: 45947 | B4: 45947 | E4: Shenice Lawrence | F4: 1 | G4: SALE50 | H4: SALE50 - % off | I4: 49.99 | J4: 0 | K4: 0 | L4: 0 | M4: 99.98 | N4: USD | O4: 4770000000 | P4: 1670000000 | Q4: ######## | S4: Shenice Lawrence | T4: 36 Washington Ave | U4: Apt 331 | V4: Carteret | W4: NJ | X4: 07008 | Y4: United States | Z4: 3829777154 | AA4: Size:40inch,Personalization:732-526-5492 Black & beige | AB4: online | AC4: listing | AD4: online_cc | AG4: 0 | AH4: SKU00010-001gray
A5: 45947 | B5: 20/10/2025 | E5: Christine Banihashemi | F5: 1 | S5: Christine Banihashemi | T5: 5540 Eden Roc Dr | V5: GRANITE BAY | W5: CA | X5: 95746 | Y5: United States | Z5: 3826836476 | AH5: SKU00010-003Ebony
A6: 45950 | B6: 20/10/2025 | E6: Jordyn Navarro | F6: 1 | S6: Jordyn Navarro | T6: 603 Wright Valley Rd | V6: SMITHVILLE | W6: MO | X6: 64089 | Y6: United States | Z6: 3830794506 | AH6: SKU00010-001Ebony
A7: 45950 | B7: 20/10/2025 | E7: Miosoti Jerez Lara | F7: 1 | S7: Miosoti Jerez Lara | T7: 26 Jennifer Dr | V7: CONCORD | W7: NH | X7: 03301 | Y7: United States | Z7: 3831344546 | AH7: SKU002Red
A8: 45949 | B8: 20/10/2025 | C8: Bamboo Fan Wall Decor, Folding Fan Headboard, Boho Wall Decor, Boho Wall Art, Oversized Fan, Bedroom Decor, Japanese Wall Art, Wall Decor | E8: Aaron Rickards | F8: 1 | G8: SALE5 | H8: SALE5 - % off | I8: 64.99 | J8: 0 | K8: 60 | L8: 0 | M8: 129.98 | N8: USD | O8: 4785331673 | P8: 1709181301 | Q8: 45949 | S8: Aaron Rickards | T8: 1A MILLENNIUM CT | V8: DROUIN | W8: VIC | X8: 3818 | Y8: Australia | Z8: 3832024462 | AA8: Size:60 inches,Color:Pink,Personalization:0400740674 | AB8: online | AC8: listing | AD8: online_cc | AG8: 0 | AH8: SKU00010-003pink
A9: 45949 | B9: 20/10/2025 | C9: Bamboo Fan Wall Decor, Folding Fan, Boho Wall Decor, Japanese Wall Art, Wall Decor Fan, Vintage fan, Boho Wall Hanging, Fan Headboard | D9: india krug (indkru) | E9: India Krug | F9: 1 | G9: SALE5 | H9: SALE5 - % off | I9: 44.99 | J9: 0 | K9: 0 | L9: 0 | M9: 89.98 | N9: USD | O9: 4785108549 | P9: 1782853472 | Q9: 45949 | S9: India Krug | T9: 201 Osage Ln | U9: Apt 24 | V9: Pittsburgh | W9: PA | X9: 15208-2755 | Y9: United States | Z9: 3831823324 | AA9: Width:31 Inches,STYLE:Terracotta,Personalization:7244647174 | AB9: online | AC9: listing | AD9: online_cc | AG9: 0 | AH9: SKU00010-000terracotta
A10: 45948 | B10: 20/10/2025 | C10: Bamboo Fan Wall Decor, Folding Fan, Boho Wall Decor, Japanese Wall Art, Wall Decor Fan, Vintage fan, Boho Wall Hanging, Fan Headboard | D10: Ruby Victoria Rose Edwards (xjef5hvt0yanxgl1) | E10: Ruby Victoria Rose Edwards | F10: 1 | G10: SALE50 | H10: SALE50 - % off | I10: 49.99 | J10: 0 | K10: 50 | L10: 0 | M10: 99.98 | N10: USD | O10: 4774535968 | P10: 1782853472 | Q10: 45948 | S10: Ruby Victoria Rose Edwards | T10: 9/188 The Parade Ascot Vale VIC 3032 | U10: 9 | V10: Ascot Vale | W10: VIC | X10: 3032 | Y10: Australia | Z10: 3830256876 | AA10: Width:40 Inches,STYLE:Terracotta,Personalization:+61478525077 | AB10: online | AC10: listing | AD10: online_cc | AG10: 0 | AH10: SKU00010-001terracotta
A11: 45948 | B11: 20/10/2025 | C11: Bamboo Fan Wall Decor, Folding Fan, Boho Wall Decor, Japanese Wall Art, Wall Decor Fan, Vintage fan, Boho Wall Hanging, Fan Headboard | D11: mervette111 | E11: Mervette Rosewell | F11: 1 | G11: SALE50 | H11: SALE50 - % off | I11: 50 | J11: 0 | K11: 50 | L11: 0 | M11: 100 | N11: USD | O11: 4783268233 | P11: 1782853472 | Q11: 45948 | S11: Mervette Rosewell | T11: 171 Bateau Bay Rd, Bateau Bay NSW 2261, Australia | V11: Bateau Bay | W11: NSW | X11: 2261 | Y11: Australia | Z11: 3832337461 | AA11: Width:31 Inches,STYLE:Terracotta,Personalization:+61466797870 | AB11: online | AC11: listing | AD11: online_cc | AG11: 0 | AH11: SKU00010-000terracotta
A12: 45948 | B12: 20/10/2025 | C12: Bamboo Fan Wall Decor, Folding Fan, Boho Wall Decor, Japanese Wall Art, Wall Decor Fan, Vintage fan, Boho Wall Hanging, Fan Headboard | D12: Sign in with Apple user (i361dj5et600jd0j) | E12: Stephanie Younes | F12: 1 | G12: SALE50 | H12: SALE50 - % off | I12: 50 | J12: 0 | K12: 0 | L12: 0 | M12: 100 | N12: USD | O12: 4783226403 | P12: 1782853472 | Q12: 45948 | S12: Stephanie Younes | T12: 1543 Dingens Avenue | V12: Windermere | W12: FL | X12: 34786 | Y12: United States | Z12: 3832306093 | AA12: Width:31 Inches,STYLE:Terracotta,Personalization:+1 321-512-9388 | AB12: online | AC12: listing | AD12: online_cc | AG12: 0 | AH12: SKU00010-000terracotta
